keyvault/__init__.py
keyvault/auth.py
keyvault/get_secrets.py
keyvault/utils.py
keyvault-0.2.1.dist-info/LICENSE
keyvault-0.2.1.dist-info/METADATA
keyvault-0.2.1.dist-info/WHEEL
keyvault-0.2.1.dist-info/top_level.txt
keyvault-0.2.1.dist-info/RECORD
