Metadata-Version: 2.1
Name: keyvault
Version: 0.2.1
Summary: A small package for handling project secrets
Home-page: https://github.com/zypp-io/keyvault
Author: Melvin Folkers, Erfan Nariman
Author-email: hello@zypp.io
Project-URL: Bug Tracker, https://github.com/zypp-io/keyvault/issues
Project-URL: Source, https://github.com/zypp-io/keyvault
Keywords: python,azure,keyvault
Classifier: Programming Language :: Python :: 3
Classifier: License :: OSI Approved :: MIT License
Classifier: Operating System :: OS Independent
Requires-Python: >=3.6
License-File: LICENSE
Requires-Dist: azure-identity>=1.7.1
Requires-Dist: azure-keyvault-secrets>=4.3.0
Requires-Dist: tqdm>=4.62.1
